CHANGES.rst
MANIFEST.in
README.rst
buildout.cfg
setup.py
plone/__init__.py
plone.formwidget.multifile.egg-info/PKG-INFO
plone.formwidget.multifile.egg-info/SOURCES.txt
plone.formwidget.multifile.egg-info/dependency_links.txt
plone.formwidget.multifile.egg-info/entry_points.txt
plone.formwidget.multifile.egg-info/namespace_packages.txt
plone.formwidget.multifile.egg-info/not-zip-safe
plone.formwidget.multifile.egg-info/requires.txt
plone.formwidget.multifile.egg-info/top_level.txt
plone/formwidget/__init__.py
plone/formwidget/multifile/README.txt
plone/formwidget/multifile/__init__.py
plone/formwidget/multifile/configure.zcml
plone/formwidget/multifile/converter.py
plone/formwidget/multifile/display.pt
plone/formwidget/multifile/file_template.pt
plone/formwidget/multifile/input.pt
plone/formwidget/multifile/interfaces.py
plone/formwidget/multifile/rebuild_i18n.sh
plone/formwidget/multifile/utils.py
plone/formwidget/multifile/widget.py
plone/formwidget/multifile/locales/plone.formwidget.multifile-manual.pot
plone/formwidget/multifile/locales/plone.formwidget.multifile.pot
plone/formwidget/multifile/locales/de/LC_MESSAGES/plone.formwidget.multifile.po
plone/formwidget/multifile/locales/es/LC_MESSAGES/plone.formwidget.multifile.po
plone/formwidget/multifile/locales/eu/LC_MESSAGES/plone.formwidget.multifile.po
plone/formwidget/multifile/locales/fr/LC_MESSAGES/plone.formwidget.multifile.po
plone/formwidget/multifile/locales/nl/LC_MESSAGES/plone.formwidget.multifile.po
plone/formwidget/multifile/locales/pt_BR/LC_MESSAGES/plone.formwidget.multifile.po
plone/formwidget/multifile/resources/multifile.js
plone/formwidget/multifile/tests/__init__.py
plone/formwidget/multifile/tests/test_doctests.py