Metadata-Version: 1.1
Name: plone.formwidget.multifile
Version: 2.0
Summary: z3c.form widget for adding multiple files
Home-page: https://github.com/plone/plone.formwidget.multifile
Author: Jonas Baumann
Author-email: j.baumann@4teamwork.ch
License: GPL
Platform: UNKNOWN
Classifier: Development Status :: 5 - Production/Stable
Classifier: Environment :: Web Environment
Classifier: Programming Language :: Python
Classifier: Programming Language :: Python :: 2.7
Classifier: Framework :: Plone
Classifier: Framework :: Plone :: 4.3
Classifier: Framework :: Plone :: 5.0
Classifier: Framework :: Plone :: 5.1
